http_utils/__init__.py
http_utils/helpers.py
http_utils/hooks.py
http_utils/session.py
http_utils/settings.py
http_utils-0.1.5.dist-info/LICENSE
http_utils-0.1.5.dist-info/METADATA
http_utils-0.1.5.dist-info/WHEEL
http_utils-0.1.5.dist-info/RECORD
