Metadata-Version: 2.1
Name: http-utils
Version: 0.1.5
Summary: Utils for HTTP requests using the requests library
Home-page: https://juntossomosmais.com.br
License: MIT
Author: Juntos Somos Mais
Author-email: labs@juntossomosmais.com.br
Maintainer: Juntos Somos Mais
Maintainer-email: labs@juntossomosmais.com.br
Requires-Python: >=3.10,<4.0
Classifier: Development Status :: 5 - Production/Stable
Classifier: Environment :: Web Environment
Classifier: Intended Audience :: Developers
Classifier: License :: OSI Approved :: MIT License
Classifier: Natural Language :: Portuguese (Brazilian)
Classifier: Operating System :: OS Independent
Classifier: Programming Language :: Python
Classifier: Programming Language :: Python :: 3
Classifier: Programming Language :: Python :: 3.10
Classifier: Programming Language :: Python :: 3.11
Classifier: Programming Language :: Python :: 3.12
Classifier: Programming Language :: Python :: 3.13
Requires-Dist: requests (>=2,<3)
Requires-Dist: urllib3 (>=2,<3)
Project-URL: Repository, https://github.com/juntossomosmais/http-utils
